fastapi_launch-1.0.0.dist-info/licenses/LICENSE
fastapi_starter/__init__.py
fastapi_starter/cli.py
fastapi_starter/template/README.md
fastapi_starter/template/alembic.ini
fastapi_starter/template/pyproject.toml
fastapi_starter/template/run.py
fastapi_starter/template/run.sh
fastapi_starter/template/uv.lock
fastapi_starter/template/app/__init__.py
fastapi_starter/template/app/main.py
fastapi_starter/template/app/db/__init__.py
fastapi_starter/template/app/db/models.py
fastapi_starter/template/app/db/session.py
fastapi_starter/template/app/lib/__init__.py
fastapi_starter/template/app/lib/config.py
fastapi_starter/template/app/lib/enums.py
fastapi_starter/template/app/lib/limiter.py
fastapi_starter/template/app/routers/__init__.py
fastapi_starter/template/app/routers/auth/__init__.py
fastapi_starter/template/app/routers/auth/functions.py
fastapi_starter/template/app/routers/auth/router.py
fastapi_starter/template/app/routers/auth/schemas.py
fastapi_starter/template/app/routers/auth/__pycache__/__init__.cpython-313.pyc
fastapi_starter/template/app/routers/auth/__pycache__/functions.cpython-313.pyc
fastapi_starter/template/app/routers/auth/__pycache__/router.cpython-313.pyc
fastapi_starter/template/app/routers/auth/__pycache__/schemas.cpython-313.pyc
fastapi_starter/template/app/routers/user/__init__.py
fastapi_starter/template/app/routers/user/router.py
fastapi_starter/template/app/routers/user/schemas.py
fastapi_starter/template/app/routers/user/__pycache__/__init__.cpython-313.pyc
fastapi_starter/template/app/routers/user/__pycache__/router.cpython-313.pyc
fastapi_starter/template/app/routers/user/__pycache__/schemas.cpython-313.pyc
fastapi_starter/template/certs/DigiCertGlobalRootCA.crt.pem
fastapi_starter/template/migrations/__init__.py
fastapi_starter/template/migrations/env.py
fastapi_starter/template/migrations/script.py.mako
fastapi_launch-1.0.0.dist-info/METADATA
fastapi_launch-1.0.0.dist-info/WHEEL
fastapi_launch-1.0.0.dist-info/entry_points.txt
fastapi_launch-1.0.0.dist-info/top_level.txt
fastapi_launch-1.0.0.dist-info/RECORD
