Metadata-Version: 2.4
Name: fastapi-launch
Version: 1.0.0
Summary: CLI tool to quickly scaffold a FastAPI project
Author-email: Robert Harris <robert.harris@devere-group.com>
License: MIT License
Project-URL: Homepage, https://github.com/dvrob/fastapi-launch
Project-URL: Repository, https://github.com/dvrob/fastapi-launch
Project-URL: Issues, https://github.com/dvrob/fastapi-launch/issues
Requires-Python: >=3.13
License-File: LICENSE
Requires-Dist: click>=8.3.0
Dynamic: license-file
